python_textunited-0.1.1.dist-info/DESCRIPTION.rst
python_textunited-0.1.1.dist-info/METADATA
python_textunited-0.1.1.dist-info/RECORD
python_textunited-0.1.1.dist-info/WHEEL
python_textunited-0.1.1.dist-info/metadata.json
python_textunited-0.1.1.dist-info/top_level.txt
textunited/__init__.py
textunited/account.py
textunited/client.py
textunited/exceptions.py
textunited/file.py
textunited/language.py
textunited/project.py
