Metadata-Version: 2.0
Name: python-textunited
Version: 0.1.1
Summary: Ten platform
Home-page: https://github.com/tenproduct/python-textunited
Author: Ten Platform
Author-email: product@tengroup.com
License: GNU General Public License v3 or later (GPLv3+)
Platform: UNKNOWN
Classifier: Development Status :: 5 - Production/Stable
Classifier: Intended Audience :: Developers
Classifier: License :: OSI Approved :: GNU General Public License v3 or later (GPLv3+)
Classifier: Operating System :: POSIX
Classifier: Operating System :: Microsoft :: Windows
Classifier: Programming Language :: Python
Classifier: Programming Language :: Python :: 3.6
Classifier: Topic :: Utilities
Requires-Dist: requests (>=2.18.4)
